httpcord/__init__.py
httpcord/asset.py
httpcord/attachment.py
httpcord/avatar.py
httpcord/bot.py
httpcord/channel.py
httpcord/command/__init__.py
httpcord/command/base.py
httpcord/command/types.py
httpcord/embed.py
httpcord/enums.py
httpcord/errors.py
httpcord/file.py
httpcord/func_protocol.py
httpcord/http.py
httpcord/interaction.py
httpcord/locale.py
httpcord/member.py
httpcord/message.py
httpcord/role.py
httpcord/types.py
httpcord/user.py
httpcord/utils/functions.py
httpcord-0.3.2.dist-info/LICENSE
httpcord-0.3.2.dist-info/METADATA
httpcord-0.3.2.dist-info/WHEEL
httpcord-0.3.2.dist-info/RECORD
