Metadata-Version: 2.3
Name: httpcord
Version: 0.3.2
Summary: A Python Discord Interaction bot API wrapper.
License: MIT
Author: Isabelle Phoebe
Author-email: izzy@uwu.gal
Requires-Python: >=3.10,<4.0
Classifier: License :: OSI Approved :: MIT License
Classifier: Programming Language :: Python :: 3
Classifier: Programming Language :: Python :: 3.10
Classifier: Programming Language :: Python :: 3.11
Classifier: Programming Language :: Python :: 3.12
Classifier: Programming Language :: Python :: 3.13
Requires-Dist: PyNaCl
Requires-Dist: aiohttp
Requires-Dist: fastapi
Requires-Dist: python-dateutil (==2.9.0.post0)
Requires-Dist: uvicorn
Project-URL: Bug Tracker, https://github.com/ijsbol/httpcord/issues
Project-URL: Homepage, https://github.com/ijsbol/httpcord
